idPettis_By_Bisca/__init__.py
idPettis_By_Bisca/idpettis_By_Bisca.py
idPettis_By_Bisca-0.0.4.dist-info/LICENSE.txt
idPettis_By_Bisca-0.0.4.dist-info/METADATA
idPettis_By_Bisca-0.0.4.dist-info/WHEEL
idPettis_By_Bisca-0.0.4.dist-info/top_level.txt
idPettis_By_Bisca-0.0.4.dist-info/RECORD
