Metadata-Version: 2.1
Name: idPettis_By_Bisca
Version: 0.0.4
Summary: IDPettis Intrinsic Dimensionality Estimation by Alberto Biscalchin
Author: Eng. Alberto Biscalchin
Author-email: biscalchin.mau.se@gmail.com
Keywords: IDPettis,intrinsic dimensionality estimation,dimensionality reduction,data analysis,machine learning,data science,nearest neighbors,high-dimensional data,dimensionality analysis,scientific computing,helix dataset,pdist,scipy,numpy,matplotlib,algorithm
Classifier: Development Status :: 4 - Beta
Classifier: Intended Audience :: Science/Research
Classifier: Programming Language :: Python :: 3
Classifier: Operating System :: OS Independent
License-File: LICENSE.txt
Requires-Dist: numpy
Requires-Dist: scipy
